{
  "OnInitSequece": [],
  "OnStartSequece": [
    {
      "TaskList": [
        {
          "$type": "RPG.GameCore.LevelPerformanceInitialize, RPG.GameCore.Config",
          "HideMonster": true,
          "HideMunicipalCrowd": true,
          "HideMunicipalOther": true,
          "HideMunicipalPedestrian": true,
          "IsClientOnly": true,
          "PerformanceType": "D",
          "ResetEnvironment": true,
          "ResetMonster": true,
          "TaskEnabled": true
        },
        {
          "$type": "RPG.GameCore.PerformanceTransition, RPG.GameCore.Config",
          "ActiveTemplateVirtualCamera": {
            "IsActive": true,
            "IsClientOnly": true
          },
          "ActiveVirtualCamera": {
            "AnchorName": "Anchor3",
            "AreaName": "LevelArea_P20211_F20211001_G199",
            "CenterPosX": -1,
            "CenterPosY": -1,
            "IsActive": true,
            "IsClientOnly": true,
            "TaskEnabled": true,
            "VCameraDitherMaxDistance": 1
          },
          "AdvNpcFaceToPlayer": {
            "ForceToStandBy": true,
            "FromDialog": true,
            "IsClientOnly": true,
            "NpcLookAtPlayer": true,
            "PlayerLookAtNpc": true,
            "StopLookAtOnGraphEnd": true,
            "TryFaceToFace": true,
            "TurnBackOnGraphEnd": true,
            "WaitFinishMode": "WaitFaceAngle"
          },
          "CaptureNpcList": [],
          "CreateNpcList": [],
          "CreateProp": {
            "GroupID": {},
            "GroupPropID": {},
            "IsClientOnly": true
          },
          "DestroyNpcList": [],
          "DestroyProp": {
            "GroupID": {},
            "ID": {},
            "IsClientOnly": true,
            "TargetType": {
              "$type": "RPG.GameCore.TargetFetchAdvPropEx, RPG.GameCore.Config"
            }
          },
          "DisactiveVCamOnGraphEnd": true,
          "IsClientOnly": true,
          "SwitchCharacterAnchor": {
            "AnchorName": {
              "Value": "Anchor1"
            },
            "AreaName": {
              "Value": "LevelArea_P20211_F20211001_G199"
            },
            "CharacterUniqueName": "LocalPlayer",
            "IsClientOnly": true,
            "IsLocalPlayer": true,
            "ResetAnimation": true,
            "ResetCamera": true,
            "TaskEnabled": true
          },
          "SwitchInTime": 0.5,
          "SwitchKeepTime": 0.5,
          "SwitchOutTime": 0.5,
          "TaskEnabled": true
        },
        {
          "$type": "RPG.GameCore.PlayAndWaitSimpleTalk, RPG.GameCore.Config",
          "IsClientOnly": true,
          "KeepDisplay": true,
          "SimpleTalkList": [
            {
              "ProtectTime": 0.3,
              "TalkSentenceID": 800324051,
              "TextSpeed": 20
            },
            {
              "ProtectTime": 0.3,
              "TalkSentenceID": 800324052,
              "TextSpeed": 20
            }
          ],
          "TaskEnabled": true
        },
        {
          "$type": "RPG.GameCore.PerformanceTransition, RPG.GameCore.Config",
          "ActiveTemplateVirtualCamera": {
            "IsActive": true,
            "IsClientOnly": true
          },
          "ActiveVirtualCamera": {
            "AnchorName": "Anchor3",
            "AreaName": "LevelArea_P20211_F20211001_G199",
            "CenterPosX": -1,
            "CenterPosY": -1,
            "IsClientOnly": true,
            "TaskEnabled": true,
            "VCameraDitherMaxDistance": 1
          },
          "AdvNpcFaceToPlayer": {
            "ForceToStandBy": true,
            "FromDialog": true,
            "IsClientOnly": true,
            "NpcLookAtPlayer": true,
            "PlayerLookAtNpc": true,
            "StopLookAtOnGraphEnd": true,
            "TryFaceToFace": true,
            "TurnBackOnGraphEnd": true,
            "WaitFinishMode": "WaitFaceAngle"
          },
          "CaptureNpcList": [],
          "CreateNpcList": [],
          "CreateProp": {
            "GroupID": {},
            "GroupPropID": {},
            "IsClientOnly": true
          },
          "DestroyNpcList": [],
          "DestroyProp": {
            "GroupID": {},
            "ID": {},
            "IsClientOnly": true,
            "TargetType": {
              "$type": "RPG.GameCore.TargetFetchAdvPropEx, RPG.GameCore.Config"
            }
          },
          "DisactiveVCamOnGraphEnd": true,
          "IsClientOnly": true,
          "SwitchCharacterAnchor": {
            "CharacterUniqueName": "LocalPlayer",
            "IsClientOnly": true,
            "ResetAnimation": true,
            "ResetCamera": true
          },
          "SwitchInTime": 0.5,
          "SwitchKeepTime": 0.5,
          "SwitchOutTime": -1,
          "TaskEnabled": true
        },
        {
          "$type": "RPG.GameCore.SetCharacterVisible, RPG.GameCore.Config",
          "IsClientOnly": true,
          "MuteColliderWhenInvisible": true,
          "TargetType": {
            "$type": "RPG.GameCore.TargetFetchAdvNpcEx, RPG.GameCore.Config",
            "FetchType": "SingleNpcByNpcID",
            "SingleNpcID": {
              "GroupID": {
                "fixedValue": {
                  "Value": 199
                }
              },
              "GroupNpcID": {
                "fixedValue": {
                  "Value": 400001
                }
              }
            }
          },
          "TaskEnabled": true,
          "Visible": true
        },
        {
          "$type": "RPG.GameCore.PerformanceTransition, RPG.GameCore.Config",
          "ActiveTemplateVirtualCamera": {
            "IsActive": true,
            "IsClientOnly": true
          },
          "ActiveVirtualCamera": {
            "AnchorName": "Anchor2",
            "AreaName": "LevelArea_P20211_F20211001_G199",
            "CenterPosX": -1,
            "CenterPosY": -1,
            "IsActive": true,
            "IsClientOnly": true,
            "TaskEnabled": true,
            "VCameraDitherMaxDistance": 1
          },
          "AdvNpcFaceToPlayer": {
            "ForceToStandBy": true,
            "FromDialog": true,
            "GroupID": 199,
            "GroupNpcID": 400001,
            "IsClientOnly": true,
            "NpcLookAtPlayer": true,
            "PlayerLookAtNpc": true,
            "StopLookAtOnGraphEnd": true,
            "TaskEnabled": true,
            "TryFaceToFace": true,
            "TurnBackOnGraphEnd": true,
            "WaitFinishMode": "WaitFaceAngle"
          },
          "CaptureNpcList": [],
          "CreateNpcList": [],
          "CreateProp": {
            "GroupID": {},
            "GroupPropID": {},
            "IsClientOnly": true
          },
          "DestroyNpcList": [],
          "DestroyProp": {
            "GroupID": {},
            "ID": {},
            "IsClientOnly": true,
            "TargetType": {
              "$type": "RPG.GameCore.TargetFetchAdvPropEx, RPG.GameCore.Config"
            }
          },
          "DisactiveVCamOnGraphEnd": true,
          "IsClientOnly": true,
          "SwitchCharacterAnchor": {
            "CharacterUniqueName": "LocalPlayer",
            "IsClientOnly": true,
            "ResetAnimation": true,
            "ResetCamera": true
          },
          "SwitchKeepTime": 0.5,
          "SwitchOutTime": 0.5,
          "TaskEnabled": true
        },
        {
          "$type": "RPG.GameCore.AdvNpcFaceToPlayer, RPG.GameCore.Config",
          "ForceToStandBy": true,
          "FromDialog": true,
          "GroupID": 199,
          "GroupNpcID": 400001,
          "IsClientOnly": true,
          "NpcLookAtPlayer": true,
          "PlayerLookAtNpc": true,
          "SteerImmediately": true,
          "StopLookAtOnGraphEnd": true,
          "TaskEnabled": true,
          "TryFaceToFace": true,
          "TurnBackOnGraphEnd": true,
          "WaitFinishMode": "WaitFaceAngle"
        },
        {
          "$type": "RPG.GameCore.PlayAndWaitSimpleTalk, RPG.GameCore.Config",
          "IsClientOnly": true,
          "KeepDisplay": true,
          "SimpleTalkList": [
            {
              "ProtectTime": 0.3,
              "TalkSentenceID": 800324053,
              "TextSpeed": 20
            }
          ],
          "TaskEnabled": true
        },
        {
          "$type": "RPG.GameCore.PlayOptionTalk, RPG.GameCore.Config",
          "IsClientOnly": true,
          "OptionList": [
            {
              "OptionIconType": "ChatContinueIcon",
              "TalkSentenceID": 800324054,
              "TriggerCustomString": "TalkSentence_800324055"
            },
            {
              "OptionIconType": "ChatContinueIcon",
              "TalkSentenceID": 800324056,
              "TriggerCustomString": "TalkSentence_800324057"
            },
            {
              "OptionIconType": "ChatContinueIcon",
              "TalkSentenceID": 800324058,
              "TriggerCustomString": "TalkSentence_800324059"
            }
          ],
          "TaskEnabled": true
        }
      ]
    },
    {
      "TaskList": [
        {
          "$type": "RPG.GameCore.WaitCustomString, RPG.GameCore.Config",
          "CustomString": {
            "Value": "TalkSentence_800324055"
          },
          "TaskEnabled": true
        },
        {
          "$type": "RPG.GameCore.PlayAndWaitSimpleTalk, RPG.GameCore.Config",
          "IsClientOnly": true,
          "KeepDisplay": true,
          "SimpleTalkList": [
            {
              "ProtectTime": 0.3,
              "TalkSentenceID": 800324055,
              "TextSpeed": 20
            }
          ],
          "TaskEnabled": true
        },
        {
          "$type": "RPG.GameCore.TriggerCustomString, RPG.GameCore.Config",
          "CustomString": {
            "Value": "TalkSentence_800324060"
          },
          "TaskEnabled": true
        }
      ]
    },
    {
      "TaskList": [
        {
          "$type": "RPG.GameCore.WaitCustomString, RPG.GameCore.Config",
          "CustomString": {
            "Value": "TalkSentence_800324057"
          },
          "TaskEnabled": true
        },
        {
          "$type": "RPG.GameCore.PlayAndWaitSimpleTalk, RPG.GameCore.Config",
          "IsClientOnly": true,
          "KeepDisplay": true,
          "SimpleTalkList": [
            {
              "ProtectTime": 0.3,
              "TalkSentenceID": 800324057,
              "TextSpeed": 20
            }
          ],
          "TaskEnabled": true
        },
        {
          "$type": "RPG.GameCore.TriggerCustomString, RPG.GameCore.Config",
          "CustomString": {
            "Value": "TalkSentence_800324060"
          },
          "TaskEnabled": true
        }
      ]
    },
    {
      "TaskList": [
        {
          "$type": "RPG.GameCore.WaitCustomString, RPG.GameCore.Config",
          "CustomString": {
            "Value": "TalkSentence_800324059"
          },
          "TaskEnabled": true
        },
        {
          "$type": "RPG.GameCore.PlayAndWaitSimpleTalk, RPG.GameCore.Config",
          "IsClientOnly": true,
          "KeepDisplay": true,
          "SimpleTalkList": [
            {
              "ProtectTime": 0.3,
              "TalkSentenceID": 800324059,
              "TextSpeed": 20
            }
          ],
          "TaskEnabled": true
        },
        {
          "$type": "RPG.GameCore.TriggerCustomString, RPG.GameCore.Config",
          "CustomString": {
            "Value": "TalkSentence_800324060"
          },
          "TaskEnabled": true
        }
      ]
    },
    {
      "TaskList": [
        {
          "$type": "RPG.GameCore.WaitCustomString, RPG.GameCore.Config",
          "CustomString": {
            "Value": "TalkSentence_800324060"
          },
          "TaskEnabled": true
        },
        {
          "$type": "RPG.GameCore.PlayAndWaitSimpleTalk, RPG.GameCore.Config",
          "IsClientOnly": true,
          "KeepDisplay": true,
          "SimpleTalkList": [
            {
              "ProtectTime": 0.3,
              "TalkSentenceID": 800324060,
              "TextSpeed": 20
            }
          ],
          "TaskEnabled": true
        },
        {
          "$type": "RPG.GameCore.PlayOptionTalk, RPG.GameCore.Config",
          "IsClientOnly": true,
          "OptionList": [
            {
              "OptionIconType": "ChatContinueIcon",
              "TalkSentenceID": 800324061,
              "TriggerCustomString": "TalkSentence_800324062"
            },
            {
              "OptionIconType": "ChatContinueIcon",
              "TalkSentenceID": 800324063,
              "TriggerCustomString": "TalkSentence_800324064"
            }
          ],
          "TaskEnabled": true
        }
      ]
    },
    {
      "TaskList": [
        {
          "$type": "RPG.GameCore.WaitCustomString, RPG.GameCore.Config",
          "CustomString": {
            "Value": "TalkSentence_800324062"
          },
          "TaskEnabled": true
        },
        {
          "$type": "RPG.GameCore.PropSetVisibility, RPG.GameCore.Config",
          "IsClientOnly": true,
          "SpecifiedRelativePaths": [],
          "TargetType": {
            "$type": "RPG.GameCore.TargetFetchAdvPropEx, RPG.GameCore.Config",
            "FetchType": "SinglePropByPropID",
            "SinglePropID": {
              "GroupID": {
                "fixedValue": {
                  "Value": 199
                }
              },
              "ID": {
                "fixedValue": {
                  "Value": 300002
                }
              }
            }
          },
          "TaskEnabled": true,
          "Visible": true
        },
        {
          "$type": "RPG.GameCore.PlayAndWaitSimpleTalk, RPG.GameCore.Config",
          "IsClientOnly": true,
          "KeepDisplay": true,
          "SimpleTalkList": [
            {
              "ProtectTime": 0.3,
              "TalkSentenceID": 800324062,
              "TextSpeed": 20
            }
          ],
          "TaskEnabled": true
        },
        {
          "$type": "RPG.GameCore.TriggerCustomString, RPG.GameCore.Config",
          "CustomString": {
            "Value": "ALL_TALK_END1"
          },
          "TaskEnabled": true
        }
      ]
    },
    {
      "TaskList": [
        {
          "$type": "RPG.GameCore.WaitCustomString, RPG.GameCore.Config",
          "CustomString": {
            "Value": "TalkSentence_800324064"
          },
          "TaskEnabled": true
        },
        {
          "$type": "RPG.GameCore.PlayAndWaitSimpleTalk, RPG.GameCore.Config",
          "IsClientOnly": true,
          "KeepDisplay": true,
          "SimpleTalkList": [
            {
              "ProtectTime": 0.3,
              "TalkSentenceID": 800324064,
              "TextSpeed": 20
            }
          ],
          "TaskEnabled": true
        },
        {
          "$type": "RPG.GameCore.PlayOptionTalk, RPG.GameCore.Config",
          "IsClientOnly": true,
          "OptionList": [
            {
              "OptionIconType": "ChatContinueIcon",
              "TalkSentenceID": 800324065,
              "TriggerCustomString": "TalkSentence_800324067"
            },
            {
              "OptionIconType": "ChatContinueIcon",
              "TalkSentenceID": 800324066,
              "TriggerCustomString": "TalkSentence_800324067"
            }
          ],
          "TaskEnabled": true
        }
      ]
    },
    {
      "TaskList": [
        {
          "$type": "RPG.GameCore.WaitCustomString, RPG.GameCore.Config",
          "CustomString": {
            "Value": "TalkSentence_800324067"
          },
          "TaskEnabled": true
        },
        {
          "$type": "RPG.GameCore.PlayAndWaitSimpleTalk, RPG.GameCore.Config",
          "IsClientOnly": true,
          "KeepDisplay": true,
          "SimpleTalkList": [
            {
              "ProtectTime": 0.3,
              "TalkSentenceID": 800324067,
              "TextSpeed": 20
            },
            {
              "ProtectTime": 0.3,
              "TalkSentenceID": 800324068,
              "TextSpeed": 20
            }
          ],
          "TaskEnabled": true
        },
        {
          "$type": "RPG.GameCore.TriggerCustomString, RPG.GameCore.Config",
          "CustomString": {
            "Value": "ALL_TALK_END2"
          },
          "TaskEnabled": true
        }
      ]
    },
    {
      "TaskList": [
        {
          "$type": "RPG.GameCore.WaitCustomString, RPG.GameCore.Config",
          "CustomString": {
            "Value": "ALL_TALK_END1"
          },
          "TaskEnabled": true
        },
        {
          "$type": "RPG.GameCore.PerformanceTransition, RPG.GameCore.Config",
          "ActiveTemplateVirtualCamera": {
            "IsActive": true,
            "IsClientOnly": true
          },
          "ActiveVirtualCamera": {
            "AnchorName": "Anchor2",
            "AreaName": "LevelArea_P20211_F20211001_G199",
            "CenterPosX": -1,
            "CenterPosY": -1,
            "IsClientOnly": true,
            "TaskEnabled": true,
            "VCameraDitherMaxDistance": 1
          },
          "AdvNpcFaceToPlayer": {
            "FinishImmadiate": true,
            "ForceToStandBy": true,
            "FromDialog": true,
            "IsClientOnly": true,
            "NpcLookAtPlayer": true,
            "PlayerLookAtNpc": true,
            "StopLookAtOnGraphEnd": true,
            "TryFaceToFace": true,
            "TurnBackOnGraphEnd": true,
            "WaitFinishMode": "WaitFaceAngle"
          },
          "CaptureNpcList": [],
          "CreateNpcList": [],
          "CreateProp": {
            "GroupID": {},
            "GroupPropID": {},
            "IsClientOnly": true
          },
          "DestroyNpcList": [],
          "DestroyProp": {
            "GroupID": {},
            "ID": {},
            "IsClientOnly": true,
            "TargetType": {
              "$type": "RPG.GameCore.TargetFetchAdvPropEx, RPG.GameCore.Config"
            }
          },
          "DisactiveVCamOnGraphEnd": true,
          "IsClientOnly": true,
          "SwitchCharacterAnchor": {
            "CharacterUniqueName": "LocalPlayer",
            "IsClientOnly": true,
            "ResetAnimation": true,
            "ResetCamera": true
          },
          "SwitchInTime": 0.5,
          "SwitchKeepTime": 0.5,
          "SwitchOutTime": -1,
          "TaskEnabled": true
        },
        {
          "$type": "RPG.GameCore.TriggerCustomString, RPG.GameCore.Config",
          "CustomString": {
            "Value": "800324002_Choose1"
          },
          "TaskEnabled": true
        },
        {
          "$type": "RPG.GameCore.EndPerformance, RPG.GameCore.Config",
          "IsClientOnly": true,
          "TaskEnabled": true
        }
      ]
    },
    {
      "TaskList": [
        {
          "$type": "RPG.GameCore.WaitCustomString, RPG.GameCore.Config",
          "CustomString": {
            "Value": "ALL_TALK_END2"
          },
          "TaskEnabled": true
        },
        {
          "$type": "RPG.GameCore.OverridePerformanceEndCrack, RPG.GameCore.Config",
          "EndWithCrack": true,
          "IsClientOnly": true,
          "TaskEnabled": true
        },
        {
          "$type": "RPG.GameCore.TriggerCustomString, RPG.GameCore.Config",
          "CustomString": {
            "Value": "800324002_Choose2"
          },
          "TaskEnabled": true
        },
        {
          "$type": "RPG.GameCore.EndPerformance, RPG.GameCore.Config",
          "IsClientOnly": true,
          "TaskEnabled": true
        }
      ]
    },
    {
      "TaskList": [
        {
          "$type": "RPG.GameCore.WaitPerformanceEnd, RPG.GameCore.Config",
          "IsClientOnly": true,
          "TaskEnabled": true
        },
        {
          "$type": "RPG.GameCore.FinishLevelGraph, RPG.GameCore.Config",
          "IsClientOnly": true,
          "TaskEnabled": true
        }
      ]
    }
  ]
}