{
  "OnInitSequece": [],
  "OnStartSequece": [
    {
      "TaskList": [
        {
          "$type": "RPG.GameCore.PlayNPCBubbleTalk, RPG.GameCore.Config",
          "BubbleTalkInfoList": [
            {
              "AutoSkipTime": 3,
              "GroupID": 9,
              "GroupNpcID": 400001,
              "TalkSentenceID": 812312701
            }
          ],
          "BubbleTalkType": "Normal",
          "InstantFinish": true,
          "IsClientOnly": true,
          "IsLoop": true,
          "LoopInterval": 3,
          "TaskEnabled": true
        }
      ]
    },
    {
      "IsLoop": true,
      "TaskList": [
        {
          "$type": "RPG.GameCore.WaitCustomString, RPG.GameCore.Config",
          "CustomString": {
            "Value": "MissionTalk_800222202"
          },
          "GoNextImmediately": true,
          "TaskEnabled": true
        },
        {
          "$type": "RPG.GameCore.TriggerBattle, RPG.GameCore.Config",
          "BattleAreaID": {
            "fixedValue": {
              "Value": 1
            }
          },
          "EventID": {
            "fixedValue": {
              "Value": 20232206
            }
          },
          "GroupID": {
            "fixedValue": {
              "Value": 2
            }
          },
          "IsClientOnly": true,
          "TaskEnabled": true
        }
      ]
    }
  ],
  "Type": "Mission"
}