{
  "OnInitSequece": [],
  "OnStartSequece": [
    {
      "TaskList": [
        {
          "$type": "RPG.GameCore.WaitCustomString, RPG.GameCore.Config",
          "CustomString": {
            "Value": "Talk_800210705"
          },
          "GoNextImmediately": true,
          "TaskEnabled": true
        },
        {
          "$type": "RPG.GameCore.FinishPerformanceMission, RPG.GameCore.Config",
          "IsClientOnly": true,
          "Key": "Mission_800210705",
          "TaskEnabled": true
        }
      ]
    },
    {
      "TaskList": [
        {
          "$type": "RPG.GameCore.WaitSecond, RPG.GameCore.Config",
          "IsClientOnly": true,
          "MaxAdvencePerTick": -1,
          "TaskEnabled": true,
          "WaitTime": {
            "fixedValue": {
              "Value": 1
            }
          }
        },
        {
          "$type": "RPG.GameCore.PlayMissionTalk, RPG.GameCore.Config",
          "IsClientOnly": true,
          "SimpleTalkList": [
            {
              "ProtectTime": 2,
              "TalkSentenceID": 800210265,
              "TextSpeed": 20
            }
          ],
          "TaskEnabled": true
        }
      ]
    }
  ],
  "Type": "Mission"
}