{
  "OnInitSequece": [],
  "OnStartSequece": [
    {
      "TaskList": [
        {
          "$type": "RPG.GameCore.WaitPerformanceEnd, RPG.GameCore.Config",
          "IsClientOnly": true,
          "TaskEnabled": true
        },
        {
          "$type": "RPG.GameCore.FinishLevelGraph, RPG.GameCore.Config",
          "IsClientOnly": true,
          "TaskEnabled": true
        }
      ]
    },
    {
      "TaskList": [
        {
          "$type": "RPG.GameCore.WaitCustomString, RPG.GameCore.Config",
          "CustomString": {
            "Value": "ALL_TALK_END"
          },
          "TaskEnabled": true
        },
        {
          "$type": "RPG.GameCore.PerformanceTransition, RPG.GameCore.Config",
          "ActiveVirtualCamera": {
            "AnchorName": "Anchor1",
            "AreaName": "LevelArea_P10102_F10102003_G29",
            "CenterPosX": -1,
            "CenterPosY": -1,
            "IsClientOnly": true,
            "TaskEnabled": true,
            "VCameraDitherMaxDistance": 1
          },
          "CaptureNpcList": [],
          "CreateNpcList": [],
          "DestroyNpcList": [],
          "DisactiveVCamOnGraphEnd": true,
          "IsClientOnly": true,
          "SwitchCharacterAnchor": {
            "AnchorName": {
              "Value": "Anchor2"
            },
            "AreaName": {
              "Value": "LevelArea_P10102_F10102003_G29"
            },
            "CharacterUniqueName": "LocalPlayer",
            "IsClientOnly": true,
            "IsLocalPlayer": true,
            "ResetAnimation": true,
            "ResetCamera": true
          },
          "SwitchInTime": 0.5,
          "SwitchKeepTime": 0.5,
          "SwitchOutTime": 0.5,
          "TaskEnabled": true
        },
        {
          "$type": "RPG.GameCore.EndPerformance, RPG.GameCore.Config",
          "IsClientOnly": true,
          "TaskEnabled": true
        }
      ]
    },
    {
      "TaskList": [
        {
          "$type": "RPG.GameCore.WaitCustomString, RPG.GameCore.Config",
          "CustomString": {
            "Value": "TalkSentence_201071927"
          },
          "TaskEnabled": true
        },
        {
          "$type": "RPG.GameCore.CharacterTriggerFreeStyle, RPG.GameCore.Config",
          "CharacterUniqueName": "LocalPlayer",
          "ForceStart": true,
          "IsClientOnly": true,
          "NormalizedTransitionDuration": 0.05,
          "StoryAvatarID": "NPC_Player",
          "StoryMotionID": 200,
          "TaskEnabled": true
        },
        {
          "$type": "RPG.GameCore.PlaySimpleTalk, RPG.GameCore.Config",
          "IsClientOnly": true,
          "KeepDisplay": true,
          "SimpleTalkList": [
            {
              "ProtectTime": 0.3,
              "TalkSentenceID": 201071927,
              "TextSpeed": 20
            },
            {
              "ProtectTime": 0.3,
              "TalkSentenceID": 201071928,
              "TextSpeed": 20
            },
            {
              "ProtectTime": 0.3,
              "TalkSentenceID": 201071929,
              "TextSpeed": 20
            },
            {
              "ProtectTime": 0.3,
              "TalkSentenceID": 201071930,
              "TextSpeed": 20
            }
          ],
          "TaskEnabled": true
        },
        {
          "$type": "RPG.GameCore.WaitSimpleTalkFinish, RPG.GameCore.Config",
          "IsClientOnly": true,
          "TaskEnabled": true
        },
        {
          "$type": "RPG.GameCore.TriggerCustomString, RPG.GameCore.Config",
          "CustomString": {
            "Value": "ALL_TALK_END"
          },
          "TaskEnabled": true
        }
      ]
    },
    {
      "TaskList": [
        {
          "$type": "RPG.GameCore.WaitCustomString, RPG.GameCore.Config",
          "CustomString": {
            "Value": "TalkSentence_201071926"
          },
          "TaskEnabled": true
        },
        {
          "$type": "RPG.GameCore.CharacterTriggerFreeStyle, RPG.GameCore.Config",
          "CharacterUniqueName": "LocalPlayer",
          "ForceStart": true,
          "IsClientOnly": true,
          "NormalizedTransitionDuration": 0.05,
          "StoryAvatarID": "NPC_Player",
          "StoryMotionID": 200,
          "TaskEnabled": true
        },
        {
          "$type": "RPG.GameCore.PlaySimpleTalk, RPG.GameCore.Config",
          "IsClientOnly": true,
          "KeepDisplay": true,
          "SimpleTalkList": [
            {
              "ProtectTime": 0.3,
              "TalkSentenceID": 201071926,
              "TextSpeed": 20
            }
          ],
          "TaskEnabled": true
        },
        {
          "$type": "RPG.GameCore.WaitSimpleTalkFinish, RPG.GameCore.Config",
          "IsClientOnly": true,
          "TaskEnabled": true
        },
        {
          "$type": "RPG.GameCore.TriggerCustomString, RPG.GameCore.Config",
          "CustomString": {
            "Value": "TalkSentence_201071927"
          },
          "TaskEnabled": true
        }
      ]
    },
    {
      "TaskList": [
        {
          "$type": "RPG.GameCore.WaitCustomString, RPG.GameCore.Config",
          "CustomString": {
            "Value": "Wait_Option_2010719_35"
          },
          "TaskEnabled": true
        },
        {
          "$type": "RPG.GameCore.PlayOptionTalk, RPG.GameCore.Config",
          "IsClientOnly": true,
          "OptionList": [
            {
              "OptionIconType": "ChatContinueIcon",
              "TalkSentenceID": 201071924,
              "TriggerCustomString": "TalkSentence_201071927"
            },
            {
              "OptionIconType": "ChatContinueIcon",
              "TalkSentenceID": 201071925,
              "TriggerCustomString": "TalkSentence_201071926"
            }
          ],
          "TaskEnabled": true
        }
      ]
    },
    {
      "TaskList": [
        {
          "$type": "RPG.GameCore.WaitCustomString, RPG.GameCore.Config",
          "CustomString": {
            "Value": "TalkSentence_201071919"
          },
          "TaskEnabled": true
        },
        {
          "$type": "RPG.GameCore.PlaySimpleTalk, RPG.GameCore.Config",
          "IsClientOnly": true,
          "KeepDisplay": true,
          "SimpleTalkList": [
            {
              "ProtectTime": 0.3,
              "TalkSentenceID": 201071919,
              "TextSpeed": 20
            },
            {
              "ProtectTime": 0.3,
              "TalkSentenceID": 201071920,
              "TextSpeed": 20
            }
          ],
          "TaskEnabled": true
        },
        {
          "$type": "RPG.GameCore.WaitSimpleTalkFinish, RPG.GameCore.Config",
          "IsClientOnly": true,
          "TaskEnabled": true
        },
        {
          "$type": "RPG.GameCore.CharacterTriggerFreeStyle, RPG.GameCore.Config",
          "CharacterUniqueName": "Natasha",
          "ForceStart": true,
          "IsClientOnly": true,
          "NormalizedTransitionDuration": 0.05,
          "StoryAvatarID": "NPC_Avatar_Lady_Natasha_00",
          "StoryMotionID": 311050236,
          "TaskEnabled": true
        },
        {
          "$type": "RPG.GameCore.PlaySimpleTalk, RPG.GameCore.Config",
          "IsClientOnly": true,
          "KeepDisplay": true,
          "SimpleTalkList": [
            {
              "ProtectTime": 0.8,
              "TalkSentenceID": 201071921,
              "TextSpeed": 20
            },
            {
              "ProtectTime": 0.3,
              "TalkSentenceID": 201071922,
              "TextSpeed": 20
            },
            {
              "ProtectTime": 0.3,
              "TalkSentenceID": 201071923,
              "TextSpeed": 20
            }
          ],
          "TaskEnabled": true
        },
        {
          "$type": "RPG.GameCore.WaitSimpleTalkFinish, RPG.GameCore.Config",
          "IsClientOnly": true,
          "TaskEnabled": true
        },
        {
          "$type": "RPG.GameCore.CharacterTriggerFreeStyle, RPG.GameCore.Config",
          "CharacterUniqueName": "Natasha",
          "ForceStart": true,
          "IsClientOnly": true,
          "NormalizedTransitionDuration": 0.05,
          "StoryAvatarID": "NPC_Avatar_Lady_Natasha_00",
          "StoryMotionID": 311050238,
          "TaskEnabled": true
        },
        {
          "$type": "RPG.GameCore.TriggerCustomString, RPG.GameCore.Config",
          "CustomString": {
            "Value": "Wait_Option_2010719_35"
          },
          "TaskEnabled": true
        }
      ]
    },
    {
      "TaskList": [
        {
          "$type": "RPG.GameCore.WaitCustomString, RPG.GameCore.Config",
          "CustomString": {
            "Value": "Wait_Option_2010719_26"
          },
          "TaskEnabled": true
        },
        {
          "$type": "RPG.GameCore.PlayOptionTalk, RPG.GameCore.Config",
          "IsClientOnly": true,
          "OptionList": [
            {
              "OptionIconType": "ChatContinueIcon",
              "TalkSentenceID": 201071917,
              "TriggerCustomString": "TalkSentence_201071919"
            },
            {
              "OptionIconType": "ChatContinueIcon",
              "TalkSentenceID": 201071918,
              "TriggerCustomString": "TalkSentence_201071919"
            }
          ],
          "TaskEnabled": true
        }
      ]
    },
    {
      "TaskList": [
        {
          "$type": "RPG.GameCore.WaitCustomString, RPG.GameCore.Config",
          "CustomString": {
            "Value": "TalkSentence_201071914"
          },
          "TaskEnabled": true
        },
        {
          "$type": "RPG.GameCore.CharacterTriggerFreeStyle, RPG.GameCore.Config",
          "CharacterUniqueName": "Natasha",
          "ForceStart": true,
          "IsClientOnly": true,
          "NormalizedTransitionDuration": 0.05,
          "StoryAvatarID": "NPC_Avatar_Lady_Natasha_00",
          "StoryMotionID": 311050200,
          "TaskEnabled": true
        },
        {
          "$type": "RPG.GameCore.PlaySimpleTalk, RPG.GameCore.Config",
          "IsClientOnly": true,
          "KeepDisplay": true,
          "SimpleTalkList": [
            {
              "ProtectTime": 0.3,
              "TalkSentenceID": 201071914,
              "TextSpeed": 20
            },
            {
              "ProtectTime": 0.3,
              "TalkSentenceID": 201071915,
              "TextSpeed": 20
            },
            {
              "ProtectTime": 0.3,
              "TalkSentenceID": 201071916,
              "TextSpeed": 20
            }
          ],
          "TaskEnabled": true
        },
        {
          "$type": "RPG.GameCore.WaitSimpleTalkFinish, RPG.GameCore.Config",
          "IsClientOnly": true,
          "TaskEnabled": true
        },
        {
          "$type": "RPG.GameCore.TriggerCustomString, RPG.GameCore.Config",
          "CustomString": {
            "Value": "Wait_Option_2010719_26"
          },
          "TaskEnabled": true
        }
      ]
    },
    {
      "TaskList": [
        {
          "$type": "RPG.GameCore.WaitCustomString, RPG.GameCore.Config",
          "CustomString": {
            "Value": "Wait_Option_2010719_19"
          },
          "TaskEnabled": true
        },
        {
          "$type": "RPG.GameCore.PlayOptionTalk, RPG.GameCore.Config",
          "IsClientOnly": true,
          "OptionList": [
            {
              "OptionIconType": "ChatContinueIcon",
              "TalkSentenceID": 201071912,
              "TriggerCustomString": "TalkSentence_201071914"
            },
            {
              "OptionIconType": "ChatContinueIcon",
              "TalkSentenceID": 201071913,
              "TriggerCustomString": "TalkSentence_201071914"
            }
          ],
          "TaskEnabled": true
        }
      ]
    },
    {
      "TaskList": [
        {
          "$type": "RPG.GameCore.WaitCustomString, RPG.GameCore.Config",
          "CustomString": {
            "Value": "TalkSentence_201071905"
          },
          "TaskEnabled": true
        },
        {
          "$type": "RPG.GameCore.PlaySimpleTalk, RPG.GameCore.Config",
          "IsClientOnly": true,
          "KeepDisplay": true,
          "SimpleTalkList": [
            {
              "ProtectTime": 0.3,
              "TalkSentenceID": 201071905,
              "TextSpeed": 20
            },
            {
              "ProtectTime": 0.3,
              "TalkSentenceID": 201071906,
              "TextSpeed": 20
            },
            {
              "ProtectTime": 0.3,
              "TalkSentenceID": 201071907,
              "TextSpeed": 20
            },
            {
              "ProtectTime": 0.3,
              "TalkSentenceID": 201071908,
              "TextSpeed": 20
            },
            {
              "ProtectTime": 0.3,
              "TalkSentenceID": 201071909,
              "TextSpeed": 20
            },
            {
              "ProtectTime": 0.3,
              "TalkSentenceID": 201071910,
              "TextSpeed": 20
            },
            {
              "ProtectTime": 0.3,
              "TalkSentenceID": 201071911,
              "TextSpeed": 20
            }
          ],
          "TaskEnabled": true
        },
        {
          "$type": "RPG.GameCore.WaitSimpleTalkFinish, RPG.GameCore.Config",
          "IsClientOnly": true,
          "TaskEnabled": true
        },
        {
          "$type": "RPG.GameCore.TriggerCustomString, RPG.GameCore.Config",
          "CustomString": {
            "Value": "Wait_Option_2010719_19"
          },
          "TaskEnabled": true
        }
      ]
    },
    {
      "TaskList": [
        {
          "$type": "RPG.GameCore.WaitCustomString, RPG.GameCore.Config",
          "CustomString": {
            "Value": "Wait_Option_2010719_8"
          },
          "TaskEnabled": true
        },
        {
          "$type": "RPG.GameCore.PlayOptionTalk, RPG.GameCore.Config",
          "IsClientOnly": true,
          "OptionList": [
            {
              "OptionIconType": "ChatContinueIcon",
              "TalkSentenceID": 201071903,
              "TriggerCustomString": "TalkSentence_201071905"
            },
            {
              "OptionIconType": "ChatContinueIcon",
              "TalkSentenceID": 201071904,
              "TriggerCustomString": "TalkSentence_201071905"
            }
          ],
          "TaskEnabled": true
        }
      ]
    },
    {
      "TaskList": [
        {
          "$type": "RPG.GameCore.WaitCustomString, RPG.GameCore.Config",
          "CustomString": {
            "Value": "TalkSentence_201071901"
          },
          "TaskEnabled": true
        },
        {
          "$type": "RPG.GameCore.CharacterTriggerFreeStyle, RPG.GameCore.Config",
          "CharacterUniqueName": "Natasha",
          "ForceStart": true,
          "IsClientOnly": true,
          "NormalizedTransitionDuration": 0.05,
          "StoryAvatarID": "NPC_Avatar_Lady_Natasha_00",
          "StoryMotionID": 311050200,
          "TaskEnabled": true
        },
        {
          "$type": "RPG.GameCore.PlaySimpleTalk, RPG.GameCore.Config",
          "IsClientOnly": true,
          "KeepDisplay": true,
          "SimpleTalkList": [
            {
              "ProtectTime": 0.3,
              "TalkSentenceID": 201071901,
              "TextSpeed": 20
            },
            {
              "ProtectTime": 0.3,
              "TalkSentenceID": 201071902,
              "TextSpeed": 20
            }
          ],
          "TaskEnabled": true
        },
        {
          "$type": "RPG.GameCore.WaitSimpleTalkFinish, RPG.GameCore.Config",
          "IsClientOnly": true,
          "TaskEnabled": true
        },
        {
          "$type": "RPG.GameCore.TriggerCustomString, RPG.GameCore.Config",
          "CustomString": {
            "Value": "Wait_Option_2010719_8"
          },
          "TaskEnabled": true
        }
      ]
    },
    {
      "TaskList": [
        {
          "$type": "RPG.GameCore.LevelPerformanceInitialize, RPG.GameCore.Config",
          "HideMonster": true,
          "HideMunicipalCrowd": true,
          "HideMunicipalOther": true,
          "HideMunicipalPedestrian": true,
          "IsClientOnly": true,
          "PerformanceType": "E",
          "ResetEnvironment": true,
          "ResetMonster": true,
          "TaskEnabled": true
        },
        {
          "$type": "RPG.GameCore.PerformanceTransition, RPG.GameCore.Config",
          "ActiveVirtualCamera": {
            "AnchorName": "Anchor1",
            "AreaName": "LevelArea_P10102_F10102003_G29",
            "CenterPosX": -1,
            "CenterPosY": -1,
            "IsActive": true,
            "IsClientOnly": true,
            "TaskEnabled": true,
            "VCameraDitherMaxDistance": 1
          },
          "CaptureNpcList": [
            {
              "CharacterUniqueName": {
                "Value": "Natasha"
              },
              "GroupID": {
                "fixedValue": {
                  "Value": 5
                }
              },
              "GroupNpcID": {
                "fixedValue": {
                  "Value": 400001
                }
              },
              "IsClientOnly": true,
              "ReleaseIfPerformanceEnd": true,
              "TaskEnabled": true
            }
          ],
          "CreateNpcList": [],
          "DestroyNpcList": [],
          "DisactiveVCamOnGraphEnd": true,
          "IsClientOnly": true,
          "SwitchCharacterAnchor": {
            "AnchorName": {
              "Value": "Anchor2"
            },
            "AreaName": {
              "Value": "LevelArea_P10102_F10102003_G29"
            },
            "CharacterUniqueName": "LocalPlayer",
            "IsClientOnly": true,
            "IsLocalPlayer": true,
            "ResetAnimation": true,
            "ResetCamera": true,
            "TaskEnabled": true
          },
          "SwitchInTime": 0.5,
          "SwitchKeepTime": 0.5,
          "SwitchOutTime": 0.5,
          "TaskEnabled": true
        },
        {
          "$type": "RPG.GameCore.AdvEntityFaceTo, RPG.GameCore.Config",
          "EnableLookAt": true,
          "EnableSteer": true,
          "ForceToStandBy": true,
          "IsClientOnly": true,
          "LookAtPoint": "Head",
          "SourceType": {
            "$type": "RPG.GameCore.TargetFetchAdvNpcEx, RPG.GameCore.Config",
            "FetchType": "SingleNpcByNpcID",
            "SingleNpcID": {
              "GroupID": {
                "fixedValue": {
                  "Value": 5
                }
              },
              "GroupNpcID": {
                "fixedValue": {
                  "Value": 400001
                }
              }
            }
          },
          "TargetType": {
            "$type": "RPG.GameCore.TargetFetchAdvLocalPlayer, RPG.GameCore.Config",
            "IncludeStoryPlayer": true
          },
          "TaskEnabled": true,
          "TurnBackOnGraphEnd": true,
          "WaitFinishMode": "WaitAnimFinish"
        },
        {
          "$type": "RPG.GameCore.TriggerCustomString, RPG.GameCore.Config",
          "CustomString": {
            "Value": "TalkSentence_201071901"
          },
          "TaskEnabled": true
        }
      ]
    }
  ]
}