{
  "OnInitSequece": [],
  "OnStartSequece": [
    {
      "TaskList": [
        {
          "$type": "RPG.GameCore.LevelPerformanceInitialize, RPG.GameCore.Config",
          "CreateCharacterList": [],
          "EntityVisiableList": [],
          "HideMunicipalOther": true,
          "IsClientOnly": true,
          "MarkStreamingItems": [],
          "PerformanceType": "D",
          "PropVisiableList": [],
          "ResetEnvironment": true,
          "ResetMonster": true,
          "TaskEnabled": true
        },
        {
          "$type": "RPG.GameCore.PlayAndWaitSimpleTalk, RPG.GameCore.Config",
          "IsClientOnly": true,
          "KeepDisplay": true,
          "SimpleTalkList": [
            {
              "ProtectTime": 0.3,
              "TalkSentenceID": 412090301,
              "TextSpeed": 20
            }
          ],
          "TaskEnabled": true
        },
        {
          "$type": "RPG.GameCore.AdvNpcFaceToPlayer, RPG.GameCore.Config",
          "FinishImmadiate": true,
          "ForceToStandBy": true,
          "GroupID": 17,
          "GroupNpcID": 400001,
          "IsClientOnly": true,
          "NpcLookAtPlayer": true,
          "PlayerLookAtNpc": true,
          "StopLookAtOnGraphEnd": true,
          "TaskEnabled": true,
          "TryFaceToFace": true,
          "TurnBackOnGraphEnd": true,
          "WaitFinishMode": "WaitFaceAngle"
        },
        {
          "$type": "RPG.GameCore.PlayOptionTalk, RPG.GameCore.Config",
          "IsClientOnly": true,
          "OptionList": [
            {
              "OptionIconType": "ChatContinueIcon",
              "TalkSentenceID": 412090302,
              "TriggerCustomString": "TalkSentence_412090303"
            },
            {
              "OptionIconType": "ChatOutIcon",
              "TalkSentenceID": 412090315,
              "TriggerCustomString": "ALL_TALK_END"
            }
          ],
          "TaskEnabled": true
        }
      ]
    },
    {
      "TaskList": [
        {
          "$type": "RPG.GameCore.CollectDataConditions, RPG.GameCore.Config",
          "CustomValueMainMissionIDList": [
            4040209
          ],
          "IsClientOnly": true,
          "MainMissionIDList": [],
          "PerformanceIDDsList": [],
          "PerformanceIDList": [],
          "TaskEnabled": true,
          "TaskIDList": []
        },
        {
          "$type": "RPG.GameCore.WaitCustomString, RPG.GameCore.Config",
          "CustomString": {
            "Value": "TalkSentence_412090303"
          },
          "TaskEnabled": true
        },
        {
          "$type": "RPG.GameCore.PlayAndWaitSimpleTalk, RPG.GameCore.Config",
          "IsClientOnly": true,
          "KeepDisplay": true,
          "SimpleTalkList": [
            {
              "ProtectTime": 0.3,
              "TalkSentenceID": 412090303,
              "TextSpeed": 20
            },
            {
              "ProtectTime": 0.3,
              "TalkSentenceID": 412090304,
              "TextSpeed": 20
            },
            {
              "ProtectTime": 0.3,
              "TalkSentenceID": 412090305,
              "TextSpeed": 20
            }
          ],
          "TaskEnabled": true
        },
        {
          "$type": "RPG.GameCore.PredicateTaskList, RPG.GameCore.Config",
          "FailedTaskList": [
            {
              "$type": "RPG.GameCore.PlayOptionTalk, RPG.GameCore.Config",
              "IsClientOnly": true,
              "OptionList": [
                {
                  "OptionIconType": "ChatOutIcon",
                  "TalkSentenceID": 412090306,
                  "TriggerCustomString": "ALL_TALK_END"
                }
              ],
              "TaskEnabled": true
            }
          ],
          "Predicate": {
            "$type": "RPG.GameCore.ByCompareMissionCustomValue, RPG.GameCore.Config",
            "EquationType": "GreaterEqual",
            "IsClientOnly": true,
            "MainMissionID": 4040209,
            "MissionCustomValue": {
              "ValidValueParamList": []
            },
            "TargetValue": 2,
            "TaskEnabled": true
          },
          "SuccessTaskList": [
            {
              "$type": "RPG.GameCore.PlayOptionTalk, RPG.GameCore.Config",
              "IsClientOnly": true,
              "OptionList": [
                {
                  "OptionIconType": "ChatContinueIcon",
                  "TalkSentenceID": 412090307,
                  "TriggerCustomString": "TalkSentence_412090308"
                }
              ],
              "TaskEnabled": true
            }
          ],
          "TaskEnabled": true
        }
      ]
    },
    {
      "TaskList": [
        {
          "$type": "RPG.GameCore.WaitCustomString, RPG.GameCore.Config",
          "CustomString": {
            "Value": "TalkSentence_412090308"
          },
          "TaskEnabled": true
        },
        {
          "$type": "RPG.GameCore.PlayAndWaitSimpleTalk, RPG.GameCore.Config",
          "IsClientOnly": true,
          "KeepDisplay": true,
          "SimpleTalkList": [
            {
              "ProtectTime": 0.3,
              "TalkSentenceID": 412090308,
              "TextSpeed": 20
            },
            {
              "ProtectTime": 0.3,
              "TalkSentenceID": 412090309,
              "TextSpeed": 20
            },
            {
              "ProtectTime": 0.3,
              "TalkSentenceID": 412090310,
              "TextSpeed": 20
            },
            {
              "ProtectTime": 0.3,
              "TalkSentenceID": 412090311,
              "TextSpeed": 20
            },
            {
              "ProtectTime": 0.3,
              "TalkSentenceID": 412090312,
              "TextSpeed": 20
            },
            {
              "ProtectTime": 0.3,
              "TalkSentenceID": 412090313,
              "TextSpeed": 20
            },
            {
              "ProtectTime": 0.3,
              "TalkSentenceID": 412090314,
              "TextSpeed": 20
            }
          ],
          "TaskEnabled": true
        },
        {
          "$type": "RPG.GameCore.TriggerCustomString, RPG.GameCore.Config",
          "CustomString": {
            "Value": "ALL_TALK_END"
          },
          "TaskEnabled": true
        }
      ]
    },
    {
      "TaskList": [
        {
          "$type": "RPG.GameCore.WaitCustomString, RPG.GameCore.Config",
          "CustomString": {
            "Value": "ALL_TALK_END"
          },
          "TaskEnabled": true
        },
        {
          "$type": "RPG.GameCore.EndPerformance, RPG.GameCore.Config",
          "IsClientOnly": true,
          "TaskEnabled": true
        }
      ]
    },
    {
      "TaskList": [
        {
          "$type": "RPG.GameCore.WaitPerformanceEnd, RPG.GameCore.Config",
          "IsClientOnly": true,
          "TaskEnabled": true
        },
        {
          "$type": "RPG.GameCore.FinishLevelGraph, RPG.GameCore.Config",
          "IsClientOnly": true,
          "TaskEnabled": true
        }
      ]
    }
  ]
}