{
  "OnInitSequece": [],
  "OnStartSequece": [
    {
      "TaskList": [
        {
          "$type": "RPG.GameCore.LevelPerformanceInitialize, RPG.GameCore.Config",
          "CreateCharacterList": [],
          "EntityVisiableList": [],
          "HideMonster": true,
          "HideMunicipalCrowd": true,
          "HideMunicipalOther": true,
          "HideMunicipalPedestrian": true,
          "IsClientOnly": true,
          "MarkStreamingItems": [],
          "PerformanceType": "E",
          "ResetEnvironment": true,
          "ResetMonster": true,
          "TaskEnabled": true
        },
        {
          "$type": "RPG.GameCore.CharacterTriggerFreeStyle, RPG.GameCore.Config",
          "CharacterUniqueName": "LocalPlayer",
          "ForceStart": true,
          "IsClientOnly": true,
          "NormalizedTransitionDuration": 0.05,
          "StoryAvatarID": "NPC_Player",
          "StoryMotionID": 200,
          "TaskEnabled": true
        },
        {
          "$type": "RPG.GameCore.PlayAndWaitSimpleTalk, RPG.GameCore.Config",
          "IsClientOnly": true,
          "KeepDisplay": true,
          "SimpleTalkList": [
            {
              "ProtectTime": 0.3,
              "TalkSentenceID": 200020240,
              "TextSpeed": 20
            }
          ],
          "TaskEnabled": true
        },
        {
          "$type": "RPG.GameCore.PlayAndWaitSimpleTalk, RPG.GameCore.Config",
          "IsClientOnly": true,
          "KeepDisplay": true,
          "SimpleTalkList": [
            {
              "ProtectTime": 0.8,
              "TalkSentenceID": 200020241,
              "TextSpeed": 20
            }
          ],
          "TaskEnabled": true
        },
        {
          "$type": "RPG.GameCore.AdvNpcFaceToPlayer, RPG.GameCore.Config",
          "FinishImmadiate": true,
          "ForceToStandBy": true,
          "FromDialog": true,
          "GroupID": 14,
          "GroupNpcID": 400002,
          "IsClientOnly": true,
          "PlayerLookAtNpc": true,
          "StopLookAtOnGraphEnd": true,
          "TaskEnabled": true,
          "TryFaceToFace": true,
          "WaitFinishMode": "WaitFaceAngle"
        },
        {
          "$type": "RPG.GameCore.EndPerformance, RPG.GameCore.Config",
          "IsClientOnly": true,
          "TaskEnabled": true
        }
      ]
    },
    {
      "TaskList": [
        {
          "$type": "RPG.GameCore.WaitPerformanceEnd, RPG.GameCore.Config",
          "IsClientOnly": true,
          "TaskEnabled": true
        },
        {
          "$type": "RPG.GameCore.FinishLevelGraph, RPG.GameCore.Config",
          "IsClientOnly": true,
          "TaskEnabled": true
        }
      ]
    }
  ]
}