{
  "AssistWayPointPackList": [],
  "FinishSubMissionList": [
    404026503
  ],
  "IsLegacyAssistWayPoint": true,
  "MainMissionID": 4040265,
  "MissionCustomValueList": [],
  "PrologueSubMssionID": 404026503,
  "StartSubMissionList": [
    404026501,
    404026502,
    404026503
  ],
  "SubMissionList": [
    {
      "CustomValueList": [],
      "CustomValueReward": [],
      "FinishActionList": [],
      "FinishType": "Talk",
      "GotoParam": [],
      "GroupIDList": [],
      "ID": 404026501,
      "LevelFloorID": 20241001,
      "LevelPlaneID": 20241,
      "MainMissionID": 4040265,
      "ParamIntList": [],
      "ParamItemList": [],
      "ParamStr1": "Mission_404026501",
      "ParamType": "Equal",
      "Progress": 1,
      "RequiredNPCSeriesIDList": [],
      "TakeParamIntList": [
        4040265
      ],
      "TakeType": "Auto"
    },
    {
      "CustomValueList": [],
      "CustomValueReward": [],
      "FinishActionList": [],
      "FinishType": "Talk",
      "GotoParam": [],
      "GroupIDList": [],
      "ID": 404026502,
      "LevelFloorID": 20241001,
      "LevelPlaneID": 20241,
      "MainMissionID": 4040265,
      "MazeFloorID": 20241001,
      "MazePlaneID": 20241,
      "ParamIntList": [],
      "ParamItemList": [],
      "ParamStr1": "Mission_404026502",
      "ParamType": "Equal",
      "Progress": 1,
      "RequiredNPCSeriesIDList": [],
      "TakeParamIntList": [
        4040265
      ],
      "TakeType": "Auto"
    },
    {
      "CustomValueList": [],
      "CustomValueReward": [],
      "FinishActionList": [],
      "FinishType": "SubMissionFinishCnt",
      "GotoParam": [],
      "GroupIDList": [],
      "ID": 404026503,
      "LevelFloorID": 20241001,
      "LevelPlaneID": 20241,
      "MainMissionID": 4040265,
      "ParamIntList": [
        404026501,
        404026502
      ],
      "ParamItemList": [],
      "ParamType": "ListContain",
      "Progress": 1,
      "RequiredNPCSeriesIDList": [],
      "TakeParamIntList": [
        4040265
      ],
      "TakeType": "Auto"
    }
  ]
}