{
  "OnInitSequece": [],
  "OnStartSequece": [
    {
      "TaskList": [
        {
          "$type": "RPG.GameCore.LevelPerformanceInitialize, RPG.GameCore.Config",
          "CreateCharacterList": [],
          "EntityVisiableList": [],
          "HideMonster": true,
          "HideMunicipalCrowd": true,
          "HideMunicipalOther": true,
          "HideMunicipalPedestrian": true,
          "IsClientOnly": true,
          "PerformanceType": "E",
          "ResetEnvironment": true,
          "ResetMonster": true,
          "TaskEnabled": true
        },
        {
          "$type": "RPG.GameCore.AdvNpcFaceToPlayer, RPG.GameCore.Config",
          "FinishImmadiate": true,
          "ForceToStandBy": true,
          "FromDialog": true,
          "GroupID": 74,
          "GroupNpcID": 400001,
          "IsClientOnly": true,
          "NpcLookAtPlayer": true,
          "PlayerLookAtNpc": true,
          "StopLookAtOnGraphEnd": true,
          "TaskEnabled": true,
          "TryFaceToFace": true,
          "TurnBackOnGraphEnd": true,
          "WaitFinishMode": "WaitFaceAngle"
        },
        {
          "$type": "RPG.GameCore.PlayAndWaitSimpleTalk, RPG.GameCore.Config",
          "IsClientOnly": true,
          "KeepDisplay": true,
          "SimpleTalkList": [
            {
              "ProtectTime": 0.3,
              "TalkSentenceID": 201214622,
              "TextSpeed": 20
            }
          ],
          "TaskEnabled": true
        },
        {
          "$type": "RPG.GameCore.PlayOptionTalk, RPG.GameCore.Config",
          "HideSelected": true,
          "IsClientOnly": true,
          "OptionList": [
            {
              "OptionIconType": "ChatContinueIcon",
              "TalkSentenceID": 201214601,
              "TriggerCustomString": "TalkSentence_201214601"
            }
          ],
          "TaskEnabled": true
        }
      ]
    },
    {
      "TaskList": [
        {
          "$type": "RPG.GameCore.WaitCustomString, RPG.GameCore.Config",
          "CustomString": {
            "Value": "TalkSentence_201214601"
          },
          "TaskEnabled": true
        },
        {
          "$type": "RPG.GameCore.PlayAndWaitSimpleTalk, RPG.GameCore.Config",
          "IsClientOnly": true,
          "KeepDisplay": true,
          "SimpleTalkList": [
            {
              "ProtectTime": 0.3,
              "TalkSentenceID": 201214602,
              "TextSpeed": 20
            },
            {
              "ProtectTime": 0.3,
              "TalkSentenceID": 201214603,
              "TextSpeed": 20
            }
          ],
          "TaskEnabled": true
        },
        {
          "$type": "RPG.GameCore.PlayOptionTalk, RPG.GameCore.Config",
          "HideSelected": true,
          "IsClientOnly": true,
          "OptionList": [
            {
              "OptionIconType": "ChatContinueIcon",
              "TalkSentenceID": 201214604,
              "TriggerCustomString": "TalkSentence_201214604"
            },
            {
              "OptionIconType": "ChatContinueIcon",
              "TalkSentenceID": 201214606,
              "TriggerCustomString": "TalkSentence_201214606"
            }
          ],
          "TaskEnabled": true
        }
      ]
    },
    {
      "TaskList": [
        {
          "$type": "RPG.GameCore.WaitCustomString, RPG.GameCore.Config",
          "CustomString": {
            "Value": "TalkSentence_201214606"
          },
          "TaskEnabled": true
        },
        {
          "$type": "RPG.GameCore.PlayAndWaitSimpleTalk, RPG.GameCore.Config",
          "IsClientOnly": true,
          "KeepDisplay": true,
          "SimpleTalkList": [
            {
              "ProtectTime": 0.3,
              "TalkSentenceID": 201214607,
              "TextSpeed": 20
            }
          ],
          "TaskEnabled": true
        },
        {
          "$type": "RPG.GameCore.EndPerformance, RPG.GameCore.Config",
          "IsClientOnly": true,
          "TaskEnabled": true
        }
      ]
    },
    {
      "TaskList": [
        {
          "$type": "RPG.GameCore.WaitCustomString, RPG.GameCore.Config",
          "CustomString": {
            "Value": "TalkSentence_201214604"
          },
          "TaskEnabled": true
        },
        {
          "$type": "RPG.GameCore.PlayAndWaitSimpleTalk, RPG.GameCore.Config",
          "IsClientOnly": true,
          "KeepDisplay": true,
          "SimpleTalkList": [
            {
              "ProtectTime": 0.3,
              "TalkSentenceID": 201214605,
              "TextSpeed": 20
            }
          ],
          "TaskEnabled": true
        },
        {
          "$type": "RPG.GameCore.EndPerformance, RPG.GameCore.Config",
          "IsClientOnly": true,
          "TaskEnabled": true
        }
      ]
    },
    {
      "TaskList": [
        {
          "$type": "RPG.GameCore.WaitPerformanceEnd, RPG.GameCore.Config",
          "IsClientOnly": true,
          "TaskEnabled": true
        },
        {
          "$type": "RPG.GameCore.FinishLevelGraph, RPG.GameCore.Config",
          "IsClientOnly": true,
          "TaskEnabled": true
        }
      ]
    }
  ]
}